draw_random_walks_meinersth/__init__.py
draw_random_walks_meinersth/main.py
draw_random_walks_meinersth-0.1.0.dist-info/METADATA
draw_random_walks_meinersth-0.1.0.dist-info/WHEEL
draw_random_walks_meinersth-0.1.0.dist-info/licenses/LICENSE
draw_random_walks_meinersth-0.1.0.dist-info/RECORD
